Metadata-Version: 2.1
Name: numba-plsa
Version: 0.0.2
Summary: Numba implementation of PLSA
Home-page: https://github.com/TnTo/numba-plsa
Author: Michele Ciruzzi
Author-email: tnto@hotmail.it
License: MIT
Platform: UNKNOWN
Classifier: Programming Language :: Python :: 3
Classifier: License :: OSI Approved :: MIT License
Requires-Python: >=3.6
License-File: LICENSE
